mcp_server_supos_ds/__init__.py
mcp_server_supos_ds/server.py
mcp_server_supos_ds-0.0.1.dist-info/METADATA
mcp_server_supos_ds-0.0.1.dist-info/WHEEL
mcp_server_supos_ds-0.0.1.dist-info/entry_points.txt
mcp_server_supos_ds-0.0.1.dist-info/licenses/LICENSE
mcp_server_supos_ds-0.0.1.dist-info/RECORD
