Metadata-Version: 2.4
Name: mcp-server-supos-ds
Version: 0.0.1
Summary: A MCP server project
Author-email: Xing Xing <xingxingumich@gmail.com>
License-File: LICENSE
Requires-Python: >=3.10
Requires-Dist: mcp>=1.0.0
Requires-Dist: numpy>=2.1.3
Requires-Dist: pandas>=2.2.3
Requires-Dist: scikit-learn>=1.5.2
Requires-Dist: scipy>=1.14.1
Requires-Dist: statsmodels>=0.14.4
